spatial_experiments_28_id/__init__.py
spatial_experiments_28_id/_version.py
spatial_experiments_28_id/movement_builder.py
spatial_experiments_28_id/run_without_gui.py
spatial_experiments_28_id/spatial_experiments_28_id.py
spatial_experiments_28_id/tests/__init__.py
spatial_experiments_28_id/tests/conftest.py
spatial_experiments_28_id/tests/test_examples.py
spatial_experiments_28_id-0.0.2.dist-info/AUTHORS.rst
spatial_experiments_28_id-0.0.2.dist-info/LICENSE
spatial_experiments_28_id-0.0.2.dist-info/METADATA
spatial_experiments_28_id-0.0.2.dist-info/WHEEL
spatial_experiments_28_id-0.0.2.dist-info/top_level.txt
spatial_experiments_28_id-0.0.2.dist-info/RECORD
