Metadata-Version: 2.1
Name: spatial-experiments-28-id
Version: 0.0.2
Summary: Easy tools for spatial experiments at 28-ID
Home-page: https://github.com/jonathanjdenney/spatial_experiments_28_id
Author: Jonathan Denney
Author-email: jonathan.denney@stonybrook.edu
License: BSD (3-clause)
Classifier: Development Status :: 2 - Pre-Alpha
Classifier: Natural Language :: English
Classifier: Programming Language :: Python :: 3
Requires-Python: >=3.9
License-File: LICENSE
License-File: AUTHORS.rst
Requires-Dist: pandas
Requires-Dist: numpy
Requires-Dist: PyQt5
Requires-Dist: pyqtgraph
